torchtrainer/__init__.py
torchtrainer/average_meter.py
torchtrainer/callbacks/__init__.py
torchtrainer/callbacks/callback_container.py
torchtrainer/callbacks/callbacks.py
torchtrainer/callbacks/checkpoint.py
torchtrainer/callbacks/csv_logger.py
torchtrainer/callbacks/early_stopping.py
torchtrainer/callbacks/metric_callback.py
torchtrainer/callbacks/progressbar.py
torchtrainer/callbacks/reducelronplateau.py
torchtrainer/callbacks/steplr.py
torchtrainer/callbacks/tensorboard.py
torchtrainer/callbacks/visdom.py
torchtrainer/metrics/__init__.py
torchtrainer/metrics/binary_accuracy.py
torchtrainer/metrics/metric.py
torchtrainer/metrics/metric_container.py
torchtrainer/trainer.py
torchtrainer/utils.py
torchtrainer-0.3.9.dist-info/WHEEL
torchtrainer-0.3.9.dist-info/METADATA
torchtrainer-0.3.9.dist-info/RECORD
